THIRD-PARTY-LICENSES
leo_aws_lambda_powertools/__init__.py
leo_aws_lambda_powertools/event_handler/__init__.py
leo_aws_lambda_powertools/event_handler/api_gateway.py
leo_aws_lambda_powertools/event_handler/appsync.py
leo_aws_lambda_powertools/event_handler/bedrock_agent.py
leo_aws_lambda_powertools/event_handler/content_types.py
leo_aws_lambda_powertools/event_handler/exceptions.py
leo_aws_lambda_powertools/event_handler/lambda_function_url.py
leo_aws_lambda_powertools/event_handler/middlewares/__init__.py
leo_aws_lambda_powertools/event_handler/middlewares/base.py
leo_aws_lambda_powertools/event_handler/middlewares/openapi_validation.py
leo_aws_lambda_powertools/event_handler/middlewares/schema_validation.py
leo_aws_lambda_powertools/event_handler/openapi/__init__.py
leo_aws_lambda_powertools/event_handler/openapi/compat.py
leo_aws_lambda_powertools/event_handler/openapi/constants.py
leo_aws_lambda_powertools/event_handler/openapi/dependant.py
leo_aws_lambda_powertools/event_handler/openapi/encoders.py
leo_aws_lambda_powertools/event_handler/openapi/exceptions.py
leo_aws_lambda_powertools/event_handler/openapi/models.py
leo_aws_lambda_powertools/event_handler/openapi/params.py
leo_aws_lambda_powertools/event_handler/openapi/pydantic_loader.py
leo_aws_lambda_powertools/event_handler/openapi/swagger_ui/__init__.py
leo_aws_lambda_powertools/event_handler/openapi/swagger_ui/html.py
leo_aws_lambda_powertools/event_handler/openapi/swagger_ui/oauth2.py
leo_aws_lambda_powertools/event_handler/openapi/swagger_ui/swagger-ui-bundle.min.js
leo_aws_lambda_powertools/event_handler/openapi/swagger_ui/swagger-ui.min.css
leo_aws_lambda_powertools/event_handler/openapi/types.py
leo_aws_lambda_powertools/event_handler/router.py
leo_aws_lambda_powertools/event_handler/types.py
leo_aws_lambda_powertools/event_handler/util.py
leo_aws_lambda_powertools/event_handler/vpc_lattice.py
leo_aws_lambda_powertools/exceptions/__init__.py
leo_aws_lambda_powertools/logging/__init__.py
leo_aws_lambda_powertools-1.0.1.dist-info/LICENSE
leo_aws_lambda_powertools-1.0.1.dist-info/METADATA
leo_aws_lambda_powertools-1.0.1.dist-info/WHEEL
leo_aws_lambda_powertools-1.0.1.dist-info/RECORD
