Metadata-Version: 2.1
Name: leo_aws_lambda_powertools
Version: 1.0.1
Summary: Powertools for AWS Lambda (Python) is a developer toolkit to implement Serverless best practices and increase developer velocity.
Home-page: https://github.com/aws-powertools/powertools-lambda-python
License: MIT
Keywords: aws_lambda_powertools,aws,tracing,logging,lambda,powertools,feature_flags,idempotency,middleware
Author: Amazon Web Services
Requires-Python: >=3.8,<4.0.0
Classifier: Development Status :: 5 - Production/Stable
Classifier: Intended Audience :: Developers
Classifier: License :: OSI Approved :: MIT License
Classifier: License :: OSI Approved :: MIT No Attribution License (MIT-0)
Classifier: Natural Language :: English
Classifier: Programming Language :: Python :: 3
Classifier: Programming Language :: Python :: 3.8
Classifier: Programming Language :: Python :: 3.9
Classifier: Programming Language :: Python :: 3.10
Classifier: Programming Language :: Python :: 3.11
Classifier: Programming Language :: Python :: 3.12
Provides-Extra: all
Provides-Extra: aws-sdk
Provides-Extra: datadog
Provides-Extra: datamasking
Provides-Extra: parser
Provides-Extra: redis
Provides-Extra: tracer
Provides-Extra: validation
Requires-Dist: aws-encryption-sdk (>=3.1.1,<4.0.0) ; extra == "all" or extra == "datamasking"
Requires-Dist: aws-xray-sdk (>=2.8.0,<3.0.0) ; extra == "tracer" or extra == "all"
Requires-Dist: boto3 (>=1.34.32,<2.0.0) ; extra == "aws-sdk"
Requires-Dist: datadog-lambda (>=4.77,<6.0) ; extra == "datadog"
Requires-Dist: fastjsonschema (>=2.14.5,<3.0.0) ; extra == "validation" or extra == "all"
Requires-Dist: jsonpath-ng (>=1.6.0,<2.0.0) ; extra == "all" or extra == "datamasking"
Requires-Dist: pydantic (>=2.0.3,<3.0.0) ; extra == "parser" or extra == "all"
Requires-Dist: redis (>=4.4,<6.0) ; extra == "redis"
Requires-Dist: typing-extensions (>=4.11.0,<5.0.0)
Project-URL: Documentation, https://docs.powertools.aws.dev/lambda/python/
Project-URL: Issue tracker, https://github.com/aws-powertools/powertools-lambda-python/issues
Project-URL: Repository, https://github.com/aws-powertools/powertools-lambda-python
Project-URL: Releases, https://github.com/aws-powertools/powertools-lambda-python/releases
